README.md
setup.py
lifxdaycycle/__init__.py
lifxdaycycle/lightmanager.py
lifxdaycycle.egg-info/PKG-INFO
lifxdaycycle.egg-info/SOURCES.txt
lifxdaycycle.egg-info/dependency_links.txt
lifxdaycycle.egg-info/entry_points.txt
lifxdaycycle.egg-info/not-zip-safe
lifxdaycycle.egg-info/requires.txt
lifxdaycycle.egg-info/top_level.txt