Metadata-Version: 1.0
Name: lifxdaycycle
Version: 0.111
Summary: changes brightness and light temperature based on the time of the day
Home-page: https://github.com/slimneotech/lifxdaycycle
Author: slimneotech
Author-email: 22907654+slimneotech@users.noreply.github.com
License: MIT
Platform: UNKNOWN
